MANIFEST.in
README.md
requirements.txt
setup.cfg
setup.py
versioneer.py
botcity/plugins/whatsapp/__init__.py
botcity/plugins/whatsapp/_version.py
botcity/plugins/whatsapp/media.py
botcity/plugins/whatsapp/plugin.py
botcity_whatsapp_plugin.egg-info/PKG-INFO
botcity_whatsapp_plugin.egg-info/SOURCES.txt
botcity_whatsapp_plugin.egg-info/dependency_links.txt
botcity_whatsapp_plugin.egg-info/requires.txt
botcity_whatsapp_plugin.egg-info/top_level.txt