Metadata-Version: 2.1
Name: botcity-whatsapp-plugin
Version: 0.1.2
Home-page: https://bitbucket.org/botcitydev/bot-whatsapp-plugin-python.git
Requires-Python: >=3.7
